deepops/__init__.py
deepops/gpu_kernels.py
deepops/ops.py
deepops/states.py
deepops/tensor.py
tests/__init__.py
tests/test_gpuops.py
deepop-0.1.dev0.dist-info/LICENSE
deepop-0.1.dev0.dist-info/METADATA
deepop-0.1.dev0.dist-info/WHEEL
deepop-0.1.dev0.dist-info/top_level.txt
deepop-0.1.dev0.dist-info/RECORD
