Metadata-Version: 2.1
Name: deepop
Version: 0.1.dev0
Summary: A mini Tensor framework for tensor operations on GPU.
Home-page: https://github.com/kartik4949/deepops
Author: Kartik Sharma
Author-email: kartik4949@gmail.com
License: UNKNOWN
Platform: UNKNOWN
Classifier: Programming Language :: Python :: 3
Classifier: License :: OSI Approved :: MIT License
Classifier: Operating System :: OS Independent
Requires-Python: >=3.8
Requires-Dist: pycuda
